degiro_client/__init__.py
degiro_client/api_client.py
degiro_client/configuration.py
degiro_client/rest.py
degiro_client/api/__init__.py
degiro_client/api/config_api.py
degiro_client/api/login_api.py
degiro_client/api/pa_api.py
degiro_client/api/product_search_api.py
degiro_client/api/reporting_api.py
degiro_client/api/settings_api.py
degiro_client/api/trading_api.py
degiro_client/models/__init__.py
degiro_client/models/any.py
degiro_client/models/check_order_response.py
degiro_client/models/check_order_response_data.py
degiro_client/models/check_order_response_data_transaction_fees.py
degiro_client/models/client_response.py
degiro_client/models/client_response_data.py
degiro_client/models/client_response_data_address.py
degiro_client/models/client_response_data_bank_account.py
degiro_client/models/client_response_data_first_contact.py
degiro_client/models/config_response.py
degiro_client/models/config_response_data.py
degiro_client/models/inline_response200.py
degiro_client/models/inline_response2001.py
degiro_client/models/inline_response2001_data.py
degiro_client/models/inline_response2002.py
degiro_client/models/inline_response2002_data.py
degiro_client/models/inline_response2002_data_desktop.py
degiro_client/models/inline_response2002_data_mobile.py
degiro_client/models/inline_response2003.py
degiro_client/models/inline_response2003_data.py
degiro_client/models/inline_response2003_data_market_page_chart_index.py
degiro_client/models/inline_response2003_data_market_page_currencies.py
degiro_client/models/inline_response2003_data_market_page_futures.py
degiro_client/models/inline_response2004.py
degiro_client/models/inline_response2004_products.py
degiro_client/models/inline_response200_data.py
degiro_client/models/login_request.py
degiro_client/models/login_response.py
degiro_client/models/one_of_any.py
degiro_client/models/order_request.py
degiro_client/models/order_response.py
degiro_client/models/order_response_data.py
degiro_client/models/update_response.py
degiro_client-0.0.1a2.dev3.dist-info/METADATA
degiro_client-0.0.1a2.dev3.dist-info/WHEEL
degiro_client-0.0.1a2.dev3.dist-info/top_level.txt
degiro_client-0.0.1a2.dev3.dist-info/RECORD
