Metadata-Version: 2.1
Name: degiro-client
Version: 0.0.1a2.dev3
Summary: Unofficial Degiro API
Home-page: https://github.com/maximdeclercq/degiro-client
Author-email: maximdeclercq00@gmail.com
License: UNKNOWN
Keywords: Swagger,Unofficial Degiro API
Platform: UNKNOWN
Requires-Dist: certifi
Requires-Dist: python-dateutil
Requires-Dist: six (>=1.10)
Requires-Dist: urllib3 (>=1.15)
